simple_pbar.py
simple_pbar-0.1.1.dist-info/licenses/LICENSE
simple_pbar-0.1.1.dist-info/METADATA
simple_pbar-0.1.1.dist-info/WHEEL
simple_pbar-0.1.1.dist-info/top_level.txt
simple_pbar-0.1.1.dist-info/RECORD
