Metadata-Version: 2.4
Name: simple-pbar
Version: 0.1.1
Summary: A simple progress bar
Home-page: https://github.com/00INDEX/simple_pbar.git
Author: 00INDEX
Author-email: zhangshuolove@live.com
Classifier: Programming Language :: Python :: 3
Classifier: License :: OSI Approved :: MIT License
Classifier: Operating System :: OS Independent
Requires-Python: >=3.6
License-File: LICENSE
Requires-Dist: rich
Dynamic: author
Dynamic: author-email
Dynamic: classifier
Dynamic: description
Dynamic: description-content-type
Dynamic: home-page
Dynamic: license-file
Dynamic: requires-dist
Dynamic: requires-python
Dynamic: summary
